AUTHORS.rst
CONTRIBUTING.rst
HISTORY.rst
LICENSE
MANIFEST.in
README.md
README.rst
setup.cfg
setup.py
docs/Makefile
docs/authors.rst
docs/conf.py
docs/contributing.rst
docs/history.rst
docs/index.rst
docs/installation.rst
docs/make.bat
docs/readme.rst
docs/usage.rst
rwswagger/__init__.py
rwswagger.egg-info/PKG-INFO
rwswagger.egg-info/SOURCES.txt
rwswagger.egg-info/dependency_links.txt
rwswagger.egg-info/not-zip-safe
rwswagger.egg-info/requires.txt
rwswagger.egg-info/top_level.txt
tests/__init__.py
tests/test_rwswagger.py