Metadata-Version: 1.1
Name: rwswagger
Version: 0.0.3
Summary: Generate swagger file from within rueckenwind
Home-page: https://github.com/FlorianLudwig/rwswagger
Author: Florian Ludwig
Author-email: f.ludwig@greyrook.com
License: Apache Software License 2.0
Keywords: rwswagger
Platform: UNKNOWN
Classifier: Development Status :: 2 - Pre-Alpha
Classifier: Intended Audience :: Developers
Classifier: License :: OSI Approved :: Apache Software License
Classifier: Natural Language :: English
Classifier: Programming Language :: Python :: 2
Classifier: Programming Language :: Python :: 2.7
Classifier: Programming Language :: Python :: 3
Classifier: Programming Language :: Python :: 3.5
